[
  {
    "kernelSource": {
      "name": "android_kernel_oplus_mt6893",
      "repo": "https://github.com/Kingslayer9988/android_kernel_oplus_mt6893.git",
      "branch": "lineage-21",
      "device": "denniz",
      "defconfig": "denniz_defconfig"
    },
    "toolchains": [
      {
        "name": "clang",
        "repo": "https://github.com/kdrag0n/proton-clang.git",
        "branch": "master",
        "binaryEnv": [
           "bin"
        ]
      }
    ],
    "enableCcache": true, 
          "params": { 
            "ARCH": "arm64", 
            "CC": "clang/bin/clang", 
            "externalCommands": { 
              "CROSS_COMPILE": "aarch64-linux-gnu-", 
              "CROSS_COMPILE_ARM32": "arm-linux-gnueabi-", 
              "AS": "clang/bin/llvm-as", 
              "AR": "clang/bin/llvm-ar",  
              "NM":"clang/bin/llvm-nm" ,  
              "OBJCOPY":"clang/bin/llvm-objcopy",  
              "OBJDUMP":"clang/bin/llvm-objdump",  
              "STRIP":"clang/bin/llvm-strip",  
              "LD":"clang/bin/ld.lld", 
              "LTO": "thin" 
      }
    },
    "AnyKernel3": {
      "use": false,
      "release": true
    },
    "enableKernelSU": true,
    "enableLXC": false
  }
]
